alliance_platform/ordered_model/__init__.py
alliance_platform/ordered_model/apps.py
alliance_platform/ordered_model/models.py
alliance_platform/ordered_model/triggers.py
alliance_platform/py.typed
alliance_platform_ordered_model-0.0.1.dist-info/METADATA
alliance_platform_ordered_model-0.0.1.dist-info/WHEEL
alliance_platform_ordered_model-0.0.1.dist-info/entry_points.txt
alliance_platform_ordered_model-0.0.1.dist-info/RECORD
