Metadata-Version: 2.1
Name: alliance-platform-ordered-model
Version: 0.0.1
Summary: Alliance Platform Ordered Model
Author-Email: Alliance Software <support@alliancesoftware.com.au>
License: BSD-2-Clause
Requires-Python: >=3.11
Requires-Dist: django-pgtrigger
Requires-Dist: Django>=4.2.11
